setup.py
tsv.py
tsv.egg-info/PKG-INFO
tsv.egg-info/SOURCES.txt
tsv.egg-info/dependency_links.txt
tsv.egg-info/top_level.txt