Metadata-Version: 1.0
Name: tsv
Version: 1.0
Summary: Tab-Separated-Value IO Library
Home-page: UNKNOWN
Author: Adam Novak
Author-email: anovak@soe.ucsc.edu
License: UNKNOWN
Platform: UNKNOWN
